sqlitecls.py
SQLiteCls-1.0.0.dist-info/LICENSE.md
SQLiteCls-1.0.0.dist-info/METADATA
SQLiteCls-1.0.0.dist-info/WHEEL
SQLiteCls-1.0.0.dist-info/top_level.txt
SQLiteCls-1.0.0.dist-info/RECORD
