Metadata-Version: 2.1
Name: SQLiteCls
Version: 1.0.0
Summary: SQLite API wrapped into a class with automatic DB schema initialisation and PRAGMA execution upon connection
Home-page: https://github.com/TheMatjaz/SQLiteCls
Author: Matjaž Guštin
Author-email: dev@matjaz.it
License: BSD
Keywords: sqlite,sqlite3,database,wrapper,class,with
Platform: UNKNOWN
Classifier: Development Status :: 5 - Production/Stable
Classifier: Intended Audience :: Developers
Classifier: License :: OSI Approved :: BSD License
Classifier: Topic :: Software Development
Classifier: Programming Language :: Python :: 3
Classifier: Programming Language :: Python :: 3.4
Classifier: Programming Language :: Python :: 3.5
Classifier: Programming Language :: Python :: 3.6
Classifier: Programming Language :: Python :: 3.7
Classifier: Programming Language :: Python :: 3.8
Classifier: Programming Language :: Python :: 3.9
Classifier: Programming Language :: Python :: 3.10
Requires-Python: >=3
